sdk/__init__.py
sdk/softfire/exp_man_client.py
sdk/softfire/__init__.py
sdk/softfire/utils.py
sdk/softfire/os_utils.py
sdk/softfire/manager.py
sdk/softfire/main.py
sdk/softfire/grpc/__init__.py
sdk/softfire/grpc/messages_pb2.py
sdk/softfire/grpc/messages_pb2_grpc.py
softfire_sdk-1.2.0.dist-info/METADATA
softfire_sdk-1.2.0.dist-info/WHEEL
softfire_sdk-1.2.0.dist-info/top_level.txt
softfire_sdk-1.2.0.dist-info/DESCRIPTION.rst
softfire_sdk-1.2.0.dist-info/RECORD
softfire_sdk-1.2.0.dist-info/metadata.json
tests/__init__.py
tests/test_sdk.py
