Metadata-Version: 2.0
Name: softfire-sdk
Version: 1.2.0
Summary: The SoftFIRE SDK for Manager
Home-page: http://softfire.eu/
Author: Lorenzo Tomasini
Author-email: lorenzo.tomasini@gmail.com
License: Apache 2
Keywords: python vnfm nfvo open baton openbaton sdk experiment manager softfire tosca openstack rest
Platform: UNKNOWN
Classifier: Development Status :: 4 - Beta
Classifier: Intended Audience :: Developers
Classifier: License :: OSI Approved :: Apache Software License
Requires-Dist: grpcio
